{"SoldList":{"pratik  khanna":{"Item1":"Lokseva Legends","Item2":0},"rohit vijjan":{"Item1":"Sanjog Warriors","Item2":0},"shibu  chetry":{"Item1":"GND 11","Item2":0},"jatin vijjan":{"Item1":"Jaggi Smashers","Item2":0},"vijay  wadhwa":{"Item1":"Sky 11","Item2":0},"ankit duggal":{"Item1":"GBD warriors","Item2":0}},"UnSoldList":{"dhruv  sharma":{"Item1":2,"Item2":"B","Item3":"C:\\Users\\Denve\\Desktop\\PPL\\Player Pics\\Player Pics\\1.jpg"},"aniket kantrod":{"Item1":2,"Item2":"B","Item3":"C:\\Users\\Denve\\Desktop\\PPL\\Player Pics\\Player Pics\\3.jpg"},"rupesh gulati":{"Item1":2,"Item2":"A","Item3":"C:\\Users\\Denve\\Desktop\\PPL\\Player Pics\\Player Pics\\4.jpg"},"vishwanath sahani":{"Item1":2,"Item2":"C","Item3":"C:\\Users\\Denve\\Desktop\\PPL\\Player Pics\\Player Pics\\5.jpg"},"vicky sahani":{"Item1":2,"Item2":"C","Item3":"C:\\Users\\Denve\\Desktop\\PPL\\Player Pics\\Player Pics\\6.jpg"},"kunal gambhir":{"Item1":2,"Item2":"C","Item3":"C:\\Users\\Denve\\Desktop\\PPL\\Player Pics\\Player Pics\\8.jpg"},"sonu gambhir":{"Item1":2,"Item2":"C","Item3":"C:\\Users\\Denve\\Desktop\\PPL\\Player Pics\\Player Pics\\9.jpg"},"akash grover":{"Item1":1,"Item2":"A","Item3":"C:\\Users\\Denve\\Desktop\\PPL\\Player Pics\\Player Pics\\10.jpg"},"kamal  kohli":{"Item1":2,"Item2":"B","Item3":"C:\\Users\\Denve\\Desktop\\PPL\\Player Pics\\Player Pics\\11.jpg"},"nimish gulati":{"Item1":2,"Item2":"A","Item3":"C:\\Users\\Denve\\Desktop\\PPL\\Player Pics\\Player Pics\\12.jpg"},"simarjeet singh  wadhwa ":{"Item1":2,"Item2":"B","Item3":"C:\\Users\\Denve\\Desktop\\PPL\\Player Pics\\Player Pics\\13.jpg"},"ranjeet singh  bhatti ":{"Item1":2,"Item2":"B","Item3":"C:\\Users\\Denve\\Desktop\\PPL\\Player Pics\\Player Pics\\14.jpg"},"ricky bakshi":{"Item1":2,"Item2":"C","Item3":"C:\\Users\\Denve\\Desktop\\PPL\\Player Pics\\Player Pics\\15.jpg"},"ravinder singh digwa":{"Item1":2,"Item2":"B","Item3":"C:\\Users\\Denve\\Desktop\\PPL\\Player Pics\\Player Pics\\16.jpg"},"gaurav  nayyar ":{"Item1":2,"Item2":"Icon","Item3":"C:\\Users\\Denve\\Desktop\\PPL\\Player Pics\\Player Pics\\17.jpg"},"naman khatri":{"Item1":2,"Item2":"B","Item3":"C:\\Users\\Denve\\Desktop\\PPL\\Player Pics\\Player Pics\\18.jpg"},"himanshu vijjan":{"Item1":2,"Item2":"B","Item3":"C:\\Users\\Denve\\Desktop\\AuctionHelper\\player-images\\default.jpg"},"suresh sahani":{"Item1":2,"Item2":"A","Item3":"C:\\Users\\Denve\\Desktop\\PPL\\Player Pics\\Player Pics\\21.jpg"},"hitesh  oberoi ":{"Item1":2,"Item2":"B","Item3":"C:\\Users\\Denve\\Desktop\\PPL\\Player Pics\\Player Pics\\22.jpg"},"virendra oberoi ":{"Item1":2,"Item2":"B","Item3":"C:\\Users\\Denve\\Desktop\\PPL\\Player Pics\\Player Pics\\23.jpg"},"purav oberoi ":{"Item1":2,"Item2":"A","Item3":"C:\\Users\\Denve\\Desktop\\AuctionHelper\\player-images\\default.jpg"},"manpreet singh  wadhwa ":{"Item1":2,"Item2":"B","Item3":"C:\\Users\\Denve\\Desktop\\PPL\\Player Pics\\Player Pics\\25.jpg"},"simarpreet  wahi ":{"Item1":2,"Item2":"C","Item3":"C:\\Users\\Denve\\Desktop\\PPL\\Player Pics\\Player Pics\\26.jpg"},"rajesh sablok":{"Item1":2,"Item2":"B","Item3":"C:\\Users\\Denve\\Desktop\\PPL\\Player Pics\\Player Pics\\27.jpg"},"vinod dewan":{"Item1":0,"Item2":"C","Item3":"C:\\Users\\Denve\\Desktop\\AuctionHelper\\player-images\\default.jpg"},"yash  dhuppad ":{"Item1":2,"Item2":"B","Item3":"C:\\Users\\Denve\\Desktop\\PPL\\Player Pics\\Player Pics\\29.jpg"},"punit vohra":{"Item1":2,"Item2":"Icon","Item3":"C:\\Users\\Denve\\Desktop\\PPL\\Player Pics\\Player Pics\\30.jpg"},"tanish kantrod":{"Item1":2,"Item2":"B","Item3":"C:\\Users\\Denve\\Desktop\\PPL\\Player Pics\\Player Pics\\31.jpg"},"iresh sahani":{"Item1":2,"Item2":"A","Item3":"C:\\Users\\Denve\\Desktop\\AuctionHelper\\player-images\\default.jpg"},"manish sahani":{"Item1":2,"Item2":"C","Item3":"C:\\Users\\Denve\\Desktop\\AuctionHelper\\player-images\\default.jpg"},"varun jaggi":{"Item1":0,"Item2":"C","Item3":"C:\\Users\\Denve\\Desktop\\PPL\\Player Pics\\Player Pics\\34.jpg"},"nakul  jaggi":{"Item1":1,"Item2":"C","Item3":"C:\\Users\\Denve\\Desktop\\PPL\\Player Pics\\Player Pics\\35.jpg"},"bhavik  ahuja ":{"Item1":0,"Item2":"Icon","Item3":"C:\\Users\\Denve\\Desktop\\PPL\\Player Pics\\Player Pics\\36.jpg"},"vijay dhingra":{"Item1":0,"Item2":"A","Item3":"C:\\Users\\Denve\\Desktop\\PPL\\Player Pics\\Player Pics\\37.jpg"},"abhishek  wai ":{"Item1":0,"Item2":"C","Item3":"C:\\Users\\Denve\\Desktop\\PPL\\Player Pics\\Player Pics\\39.jpg"},"ravinder singh  narang ":{"Item1":2,"Item2":"C","Item3":"C:\\Users\\Denve\\Desktop\\PPL\\Player Pics\\Player Pics\\40.jpg"},"jasmit  singh":{"Item1":1,"Item2":"A","Item3":"C:\\Users\\Denve\\Desktop\\PPL\\Player Pics\\Player Pics\\41.jpg"},"pritam  singh":{"Item1":2,"Item2":"A","Item3":"C:\\Users\\Denve\\Desktop\\PPL\\Player Pics\\Player Pics\\42.jpg"},"sanjay ahuja":{"Item1":2,"Item2":"C","Item3":"C:\\Users\\Denve\\Desktop\\AuctionHelper\\player-images\\default.jpg"},"deepesh  kantrod":{"Item1":2,"Item2":"A","Item3":"C:\\Users\\Denve\\Desktop\\PPL\\Player Pics\\Player Pics\\44.jpg"},"tanay  kumar ":{"Item1":2,"Item2":"B","Item3":"C:\\Users\\Denve\\Desktop\\PPL\\Player Pics\\Player Pics\\45.jpg"},"raj chawla":{"Item1":2,"Item2":"C","Item3":"C:\\Users\\Denve\\Desktop\\PPL\\Player Pics\\Player Pics\\46.jpg"},"monty  vohra":{"Item1":2,"Item2":"B","Item3":"C:\\Users\\Denve\\Desktop\\PPL\\Player Pics\\Player Pics\\47.jpg"},"hitesh  gupta ":{"Item1":2,"Item2":"C","Item3":"C:\\Users\\Denve\\Desktop\\PPL\\Player Pics\\Player Pics\\48.jpg"},"punit batra":{"Item1":0,"Item2":"C","Item3":"C:\\Users\\Denve\\Desktop\\PPL\\Player Pics\\Player Pics\\49.jpg"},"rohit sahani":{"Item1":2,"Item2":"A","Item3":"C:\\Users\\Denve\\Desktop\\PPL\\Player Pics\\Player Pics\\50.jpg"},"suresh  wadhwa ":{"Item1":2,"Item2":"B","Item3":"C:\\Users\\Denve\\Desktop\\PPL\\Player Pics\\Player Pics\\51.jpg"},"sushil  jaggi":{"Item1":2,"Item2":"A","Item3":"C:\\Users\\Denve\\Desktop\\PPL\\Player Pics\\Player Pics\\52.jpg"},"nitin gurli ":{"Item1":2,"Item2":"B","Item3":"C:\\Users\\Denve\\Desktop\\PPL\\Player Pics\\Player Pics\\53.jpg"},"yash sanadeep ahuja":{"Item1":2,"Item2":"C","Item3":"C:\\Users\\Denve\\Desktop\\AuctionHelper\\player-images\\default.jpg"},"viraj vijjan":{"Item1":2,"Item2":"A","Item3":"C:\\Users\\Denve\\Desktop\\PPL\\Player Pics\\Player Pics\\56.jpg"},"anuj vijjan":{"Item1":2,"Item2":"A","Item3":"C:\\Users\\Denve\\Desktop\\PPL\\Player Pics\\Player Pics\\57.jpg"},"akshad vijjan":{"Item1":1,"Item2":"B","Item3":"C:\\Users\\Denve\\Desktop\\PPL\\Player Pics\\Player Pics\\58.jpg"},"dinesh bhatiya ":{"Item1":1,"Item2":"B","Item3":"C:\\Users\\Denve\\Desktop\\PPL\\Player Pics\\Player Pics\\59.jpg"},"sawan  chhabra ":{"Item1":2,"Item2":"B","Item3":"C:\\Users\\Denve\\Desktop\\PPL\\Player Pics\\Player Pics\\60.jpg"},"aditya  ahuja":{"Item1":2,"Item2":"B","Item3":"C:\\Users\\Denve\\Desktop\\PPL\\Player Pics\\Player Pics\\61.jpg"},"sharneet singh":{"Item1":2,"Item2":"C","Item3":"C:\\Users\\Denve\\Desktop\\PPL\\Player Pics\\Player Pics\\63.jpg"},"abhimanyu  nayyar":{"Item1":2,"Item2":"A","Item3":"C:\\Users\\Denve\\Desktop\\AuctionHelper\\player-images\\default.jpg"},"ankit ( gurpreet singh) saluja":{"Item1":2,"Item2":"C","Item3":"C:\\Users\\Denve\\Desktop\\PPL\\Player Pics\\Player Pics\\64.jpg"},"sherry oberai":{"Item1":2,"Item2":"B","Item3":"C:\\Users\\Denve\\Desktop\\AuctionHelper\\player-images\\default.jpg"},"sunny ahuja":{"Item1":2,"Item2":"C","Item3":"C:\\Users\\Denve\\Desktop\\PPL\\Player Pics\\Player Pics\\65.jpg"},"manish_ahuja":{"Item1":2,"Item2":"B","Item3":"C:\\Users\\Denve\\Desktop\\PPL\\Player Pics\\Player Pics\\67.jpg"},"dhiraj nayyar":{"Item1":2,"Item2":"C","Item3":"C:\\Users\\Denve\\Desktop\\PPL\\Player Pics\\Player Pics\\75.jpg"},"ronak kaisar":{"Item1":2,"Item2":"A","Item3":"C:\\Users\\Denve\\Desktop\\AuctionHelper\\player-images\\default.jpg"},"harsh oberoi":{"Item1":2,"Item2":"C","Item3":"C:\\Users\\Denve\\Desktop\\PPL\\Player Pics\\Player Pics\\77.jpg"},"pankaj jaggi":{"Item1":0,"Item2":"B","Item3":"C:\\Users\\Denve\\Desktop\\PPL\\Player Pics\\Player Pics\\79.jpg"},"jahan khanna":{"Item1":2,"Item2":"A","Item3":"C:\\Users\\Denve\\Desktop\\PPL\\Player Pics\\Player Pics\\80.jpg"},"rupesh  kantrod ":{"Item1":0,"Item2":"A","Item3":"C:\\Users\\Denve\\Desktop\\PPL\\Player Pics\\Player Pics\\81.jpg"},"rishi  grover ":{"Item1":0,"Item2":"A","Item3":"C:\\Users\\Denve\\Desktop\\PPL\\Player Pics\\Player Pics\\82.jpg"},"kuldeepsingh  grover":{"Item1":2,"Item2":"B","Item3":"C:\\Users\\Denve\\Desktop\\PPL\\Player Pics\\Player Pics\\83.jpg"},"jasveer grover":{"Item1":2,"Item2":"C","Item3":"C:\\Users\\Denve\\Desktop\\AuctionHelper\\player-images\\default.jpg"},"tejas  jaggi ":{"Item1":0,"Item2":"B","Item3":"C:\\Users\\Denve\\Desktop\\PPL\\Player Pics\\Player Pics\\85.jpg"},"rounak oberoi":{"Item1":2,"Item2":"B","Item3":"C:\\Users\\Denve\\Desktop\\PPL\\Player Pics\\Player Pics\\86.jpg"},"krishna jaggi":{"Item1":1,"Item2":"B","Item3":"C:\\Users\\Denve\\Desktop\\PPL\\Player Pics\\Player Pics\\87.jpg"},"nitesh  jaggi":{"Item1":2,"Item2":"A","Item3":"C:\\Users\\Denve\\Desktop\\PPL\\Player Pics\\Player Pics\\88.jpg"},"pratik jaggi":{"Item1":0,"Item2":"B","Item3":"C:\\Users\\Denve\\Desktop\\PPL\\Player Pics\\Player Pics\\89.jpg"},"yogesh jaggi ":{"Item1":1,"Item2":"C","Item3":"C:\\Users\\Denve\\Desktop\\PPL\\Player Pics\\Player Pics\\90.jpg"},"sumesh  jaggi ":{"Item1":1,"Item2":"B","Item3":"C:\\Users\\Denve\\Desktop\\PPL\\Player Pics\\Player Pics\\91.jpg"},"rajesh  jaggi ":{"Item1":1,"Item2":"C","Item3":"C:\\Users\\Denve\\Desktop\\PPL\\Player Pics\\Player Pics\\92.jpg"},"puneet bhutani":{"Item1":2,"Item2":"B","Item3":"C:\\Users\\Denve\\Desktop\\AuctionHelper\\player-images\\default.jpg"},"kapil  sahani":{"Item1":1,"Item2":"C","Item3":"C:\\Users\\Denve\\Desktop\\PPL\\Player Pics\\Player Pics\\94.jpg"},"himang nayyar ":{"Item1":2,"Item2":"C","Item3":"C:\\Users\\Denve\\Desktop\\PPL\\Player Pics\\Player Pics\\95.jpg"},"amit  thapar ":{"Item1":0,"Item2":"C","Item3":"C:\\Users\\Denve\\Desktop\\PPL\\Player Pics\\Player Pics\\96.jpg"},"amandeep singh  gill":{"Item1":2,"Item2":"B","Item3":"C:\\Users\\Denve\\Desktop\\PPL\\Player Pics\\Player Pics\\97.jpg"},"rajbeer singh shahi":{"Item1":2,"Item2":"A","Item3":"C:\\Users\\Denve\\Desktop\\PPL\\Player Pics\\Player Pics\\98.jpg"},"amarjit singh shahi":{"Item1":2,"Item2":"C","Item3":"C:\\Users\\Denve\\Desktop\\PPL\\Player Pics\\Player Pics\\99.jpg"},"rishi  kapoor":{"Item1":2,"Item2":"C","Item3":"C:\\Users\\Denve\\Desktop\\AuctionHelper\\player-images\\default.jpg"},"maahhir  kapoor":{"Item1":0,"Item2":"A","Item3":"C:\\Users\\Denve\\Desktop\\PPL\\Player Pics\\Player Pics\\101.jpg"},"bablusingh  rajput":{"Item1":2,"Item2":"B","Item3":"C:\\Users\\Denve\\Desktop\\PPL\\Player Pics\\Player Pics\\102.jpg"},"saurabh  ahuja":{"Item1":0,"Item2":"B","Item3":"C:\\Users\\Denve\\Desktop\\PPL\\Player Pics\\Player Pics\\103.jpg"},"shyam sablok":{"Item1":0,"Item2":"C","Item3":"C:\\Users\\Denve\\Desktop\\AuctionHelper\\player-images\\default.jpg"},"piyush  kantrod":{"Item1":2,"Item2":"A","Item3":"C:\\Users\\Denve\\Desktop\\PPL\\Player Pics\\Player Pics\\105.jpg"},"dhruv kantrod":{"Item1":2,"Item2":"C","Item3":"C:\\Users\\Denve\\Desktop\\PPL\\Player Pics\\Player Pics\\106.jpg"},"ricky  kantrod":{"Item1":2,"Item2":"B","Item3":"C:\\Users\\Denve\\Desktop\\PPL\\Player Pics\\Player Pics\\107.jpg"},"jogesh kumar ":{"Item1":2,"Item2":"C","Item3":"C:\\Users\\Denve\\Desktop\\PPL\\Player Pics\\Player Pics\\108.jpg"},"yogesh dewan":{"Item1":0,"Item2":"B","Item3":"C:\\Users\\Denve\\Desktop\\PPL\\Player Pics\\Player Pics\\109.jpg"},"narayan arora":{"Item1":2,"Item2":"A","Item3":"C:\\Users\\Denve\\Desktop\\PPL\\Player Pics\\Player Pics\\110.jpg"},"vishnu duggal":{"Item1":2,"Item2":"B","Item3":"C:\\Users\\Denve\\Desktop\\PPL\\Player Pics\\Player Pics\\111.jpg"},"harsh  batra ":{"Item1":0,"Item2":"C","Item3":"C:\\Users\\Denve\\Desktop\\PPL\\Player Pics\\Player Pics\\112.jpg"},"shaunak punjabi":{"Item1":2,"Item2":"C","Item3":"C:\\Users\\Denve\\Desktop\\PPL\\Player Pics\\Player Pics\\113.jpg"},"vishal bakshi":{"Item1":2,"Item2":"C","Item3":"C:\\Users\\Denve\\Desktop\\PPL\\Player Pics\\Player Pics\\114.jpg"},"adhyayan bakshi":{"Item1":2,"Item2":"B","Item3":"C:\\Users\\Denve\\Desktop\\AuctionHelper\\player-images\\default.jpg"},"mohit punjabi":{"Item1":0,"Item2":"C","Item3":"C:\\Users\\Denve\\Desktop\\PPL\\Player Pics\\Player Pics\\116.jpg"},"rohit bhatia":{"Item1":2,"Item2":"C","Item3":"C:\\Users\\Denve\\Desktop\\AuctionHelper\\player-images\\default.jpg"},"ritik jaggi":{"Item1":2,"Item2":"B","Item3":"C:\\Users\\Denve\\Desktop\\PPL\\Player Pics\\Player Pics\\118.jpg"},"arjun jaggi":{"Item1":2,"Item2":"B","Item3":"C:\\Users\\Denve\\Desktop\\PPL\\Player Pics\\Player Pics\\119.jpg"},"randeep singh amar":{"Item1":2,"Item2":"A","Item3":"C:\\Users\\Denve\\Desktop\\PPL\\Player Pics\\Player Pics\\120.jpg"},"saurabh  punjabi":{"Item1":2,"Item2":"B","Item3":"C:\\Users\\Denve\\Desktop\\AuctionHelper\\player-images\\default.jpg"},"sagar kumar ":{"Item1":1,"Item2":"B","Item3":"C:\\Users\\Denve\\Desktop\\AuctionHelper\\player-images\\default.jpg"},"gaurav  kantrod ":{"Item1":0,"Item2":"C","Item3":"C:\\Users\\Denve\\Desktop\\PPL\\Player Pics\\Player Pics\\123.jpg"},"parab gulati ":{"Item1":2,"Item2":"B","Item3":"C:\\Users\\Denve\\Desktop\\PPL\\Player Pics\\Player Pics\\124.jpg"},"shivkumar khurana":{"Item1":2,"Item2":"Icon","Item3":"C:\\Users\\Denve\\Desktop\\PPL\\Player Pics\\Player Pics\\125.jpg"},"jitender singh  bhatia":{"Item1":2,"Item2":"A","Item3":"C:\\Users\\Denve\\Desktop\\PPL\\Player Pics\\Player Pics\\126.jpg"},"manpreet dhuppar":{"Item1":2,"Item2":"C","Item3":"C:\\Users\\Denve\\Desktop\\PPL\\Player Pics\\Player Pics\\127.jpg"},"simran gambhir":{"Item1":2,"Item2":"B","Item3":"C:\\Users\\Denve\\Desktop\\PPL\\Player Pics\\Player Pics\\128.jpg"},"karan  ahuja":{"Item1":0,"Item2":"C","Item3":"C:\\Users\\Denve\\Desktop\\PPL\\Player Pics\\Player Pics\\129.jpg"},"major chawla":{"Item1":2,"Item2":"C","Item3":"C:\\Users\\Denve\\Desktop\\PPL\\Player Pics\\Player Pics\\130.jpg"},"manish ahuja":{"Item1":2,"Item2":"C","Item3":"C:\\Users\\Denve\\Desktop\\PPL\\Player Pics\\Player Pics\\131.jpg"},"akshay  gulati ":{"Item1":2,"Item2":"B","Item3":"C:\\Users\\Denve\\Desktop\\PPL\\Player Pics\\Player Pics\\132.jpg"},"tarun  mahendru":{"Item1":1,"Item2":"C","Item3":"C:\\Users\\Denve\\Desktop\\PPL\\Player Pics\\Player Pics\\133.jpg"},"gurpreet singh digwa":{"Item1":2,"Item2":"B","Item3":"C:\\Users\\Denve\\Desktop\\PPL\\Player Pics\\Player Pics\\134.jpg"},"jaspal singh kandhari":{"Item1":2,"Item2":"B","Item3":"C:\\Users\\Denve\\Desktop\\PPL\\Player Pics\\Player Pics\\135.jpg"},"pradeep singh":{"Item1":2,"Item2":"A","Item3":"C:\\Users\\Denve\\Desktop\\PPL\\Player Pics\\Player Pics\\136.jpg"},"sarbjot singh digwa":{"Item1":2,"Item2":"A","Item3":"C:\\Users\\Denve\\Desktop\\PPL\\Player Pics\\Player Pics\\137.jpg"},"gagandeep singh digwa":{"Item1":2,"Item2":"B","Item3":"C:\\Users\\Denve\\Desktop\\AuctionHelper\\player-images\\default.jpg"},"gurpreet singh bhatti ":{"Item1":0,"Item2":"B","Item3":"C:\\Users\\Denve\\Desktop\\AuctionHelper\\player-images\\default.jpg"},"balveer singh hira":{"Item1":2,"Item2":"A","Item3":"C:\\Users\\Denve\\Desktop\\AuctionHelper\\player-images\\default.jpg"},"avtar singh hira":{"Item1":2,"Item2":"A","Item3":"C:\\Users\\Denve\\Desktop\\AuctionHelper\\player-images\\default.jpg"},"baljeet birla":{"Item1":2,"Item2":"C","Item3":"C:\\Users\\Denve\\Desktop\\AuctionHelper\\player-images\\default.jpg"},"joshal gulati":{"Item1":2,"Item2":"C","Item3":"C:\\Users\\Denve\\Desktop\\PPL\\Player Pics\\Player Pics\\143.jpg"},"romi rajan arora":{"Item1":2,"Item2":"C","Item3":"C:\\Users\\Denve\\Desktop\\PPL\\Player Pics\\Player Pics\\144.jpg"},"nitin virmani":{"Item1":2,"Item2":"C","Item3":"C:\\Users\\Denve\\Desktop\\PPL\\Player Pics\\Player Pics\\145.jpg"},"arjun mandan":{"Item1":2,"Item2":"C","Item3":"C:\\Users\\Denve\\Desktop\\AuctionHelper\\player-images\\default.jpg"},"manender singh":{"Item1":2,"Item2":"C","Item3":"C:\\Users\\Denve\\Desktop\\AuctionHelper\\player-images\\default.jpg"},"maninder digwa":{"Item1":2,"Item2":"C","Item3":"C:\\Users\\Denve\\Desktop\\AuctionHelper\\player-images\\default.jpg"}},"Details":{"Lokseva Legends":{"TotalPurse":2500000,"PurseUtilized":0,"PurseRem":2500000,"MinBaseRequired":1300000,"MinimumTeamReq":{"ReqCount":13,"diCategoryWiseCount":{"Icon":0,"A":3,"B":5,"C":4,"Unknown":0}},"isTopUp1Used":false,"isTopUp2used":false,"playerList":{"pratik  khanna":{"PlayerCategory":"Icon","PriceSold":0}}},"GND 11":{"TotalPurse":2500000,"PurseUtilized":0,"PurseRem":2500000,"MinBaseRequired":1300000,"MinimumTeamReq":{"ReqCount":13,"diCategoryWiseCount":{"Icon":0,"A":3,"B":5,"C":4,"Unknown":0}},"isTopUp1Used":false,"isTopUp2used":false,"playerList":{"shibu  chetry":{"PlayerCategory":"Icon","PriceSold":0}}},"Simba":{"TotalPurse":2500000,"PurseUtilized":0,"PurseRem":2500000,"MinBaseRequired":1300000,"MinimumTeamReq":{"ReqCount":14,"diCategoryWiseCount":{"Icon":1,"A":3,"B":5,"C":4,"Unknown":0}},"isTopUp1Used":false,"isTopUp2used":false,"playerList":{}},"RR STARS":{"TotalPurse":2500000,"PurseUtilized":0,"PurseRem":2500000,"MinBaseRequired":1300000,"MinimumTeamReq":{"ReqCount":14,"diCategoryWiseCount":{"Icon":1,"A":3,"B":5,"C":4,"Unknown":0}},"isTopUp1Used":false,"isTopUp2used":false,"playerList":{}},"Sky 11":{"TotalPurse":2500000,"PurseUtilized":0,"PurseRem":2500000,"MinBaseRequired":1300000,"MinimumTeamReq":{"ReqCount":13,"diCategoryWiseCount":{"Icon":0,"A":3,"B":5,"C":4,"Unknown":0}},"isTopUp1Used":false,"isTopUp2used":false,"playerList":{"vijay  wadhwa":{"PlayerCategory":"Icon","PriceSold":0}}},"Jaggi Smashers":{"TotalPurse":2500000,"PurseUtilized":0,"PurseRem":2500000,"MinBaseRequired":1300000,"MinimumTeamReq":{"ReqCount":13,"diCategoryWiseCount":{"Icon":0,"A":3,"B":5,"C":4,"Unknown":0}},"isTopUp1Used":false,"isTopUp2used":false,"playerList":{"jatin vijjan":{"PlayerCategory":"Icon","PriceSold":0}}},"GBD warriors":{"TotalPurse":2500000,"PurseUtilized":0,"PurseRem":2500000,"MinBaseRequired":1300000,"MinimumTeamReq":{"ReqCount":13,"diCategoryWiseCount":{"Icon":0,"A":3,"B":5,"C":4,"Unknown":0}},"isTopUp1Used":false,"isTopUp2used":false,"playerList":{"ankit duggal":{"PlayerCategory":"Icon","PriceSold":0}}},"Thapar 11":{"TotalPurse":2500000,"PurseUtilized":0,"PurseRem":2500000,"MinBaseRequired":1300000,"MinimumTeamReq":{"ReqCount":14,"diCategoryWiseCount":{"Icon":1,"A":3,"B":5,"C":4,"Unknown":0}},"isTopUp1Used":false,"isTopUp2used":false,"playerList":{}},"CHETAK KAMDA KINGS":{"TotalPurse":2500000,"PurseUtilized":0,"PurseRem":2500000,"MinBaseRequired":1300000,"MinimumTeamReq":{"ReqCount":14,"diCategoryWiseCount":{"Icon":1,"A":3,"B":5,"C":4,"Unknown":0}},"isTopUp1Used":false,"isTopUp2used":false,"playerList":{}},"Sanjog Warriors":{"TotalPurse":2500000,"PurseUtilized":0,"PurseRem":2500000,"MinBaseRequired":1300000,"MinimumTeamReq":{"ReqCount":13,"diCategoryWiseCount":{"Icon":0,"A":3,"B":5,"C":4,"Unknown":0}},"isTopUp1Used":false,"isTopUp2used":false,"playerList":{"rohit vijjan":{"PlayerCategory":"Icon","PriceSold":0}}}}}